galactica/__init__.py
galactica/disk.py
galactica/halo.py
galactica/main_initial.py
galactica-0.0.1a0.dist-info/LICENSE
galactica-0.0.1a0.dist-info/METADATA
galactica-0.0.1a0.dist-info/WHEEL
galactica-0.0.1a0.dist-info/top_level.txt
galactica-0.0.1a0.dist-info/RECORD
