Metadata-Version: 2.1
Name: galactica
Version: 0.0.1a0
Summary: Galactic multiphase chemical evolution model
Home-page: https://github.com/xuanxu/galactica
Author: Juanjo Bazán
Author-email: hello@juanjobazan.com
License: MIT
Download-URL: https://github.com/xuanxu/galactica
Keywords: galaxies,models,astrophysics
Platform: UNKNOWN
Classifier: Development Status :: 2 - Pre-Alpha
Classifier: Intended Audience :: Science/Research
Classifier: Intended Audience :: Education
Classifier: License :: OSI Approved :: MIT License
Classifier: Operating System :: OS Independent
Classifier: Programming Language :: Python
Classifier: Programming Language :: Python :: 3
Classifier: Programming Language :: Python :: 3.6
Classifier: Programming Language :: Python :: 3.7
Classifier: Programming Language :: Python :: 3.8
Classifier: Programming Language :: Python :: Implementation :: CPython
Classifier: Topic :: Scientific/Engineering :: Astronomy
Classifier: Topic :: Scientific/Engineering :: Physics
Requires-Python: >=3.6
Requires-Dist: pyyaml (>=5.1)
Requires-Dist: numpy (>=1.16)
Requires-Dist: scipy (>=1.2)
Provides-Extra: dev
Requires-Dist: pytest ; extra == 'dev'
Requires-Dist: pytest-mock ; extra == 'dev'
Requires-Dist: pytest-cov ; extra == 'dev'
